{"nodes": [{"id": "branches", "label": "branches.rs", "file_type": "code", "source_file": "src/linux_terminal/git/branches.rs", "source_location": "L1"}, {"id": "branches_build_branches_view", "label": "build_branches_view()", "file_type": "code", "source_file": "src/linux_terminal/git/branches.rs", "source_location": "L13"}, {"id": "branches_refresh_branches", "label": "refresh_branches()", "file_type": "code", "source_file": "src/linux_terminal/git/branches.rs", "source_location": "L113"}, {"id": "branches_build_branch_row", "label": "build_branch_row()", "file_type": "code", "source_file": "src/linux_terminal/git/branches.rs", "source_location": "L144"}, {"id": "branches_build_remote_branch_row", "label": "build_remote_branch_row()", "file_type": "code", "source_file": "src/linux_terminal/git/branches.rs", "source_location": "L244"}, {"id": "branches_clear_list", "label": "clear_list()", "file_type": "code", "source_file": "src/linux_terminal/git/branches.rs", "source_location": "L265"}, {"id": "branches_branchwidgets", "label": "BranchWidgets", "file_type": "code", "source_file": "src/linux_terminal/git/branches.rs", "source_location": "L271"}], "edges": [{"source": "branches", "target": "rc", "relation": "imports_from", "confidence": "EXTRACTED", "source_file": "src/linux_terminal/git/branches.rs", "source_location": "L1", "weight": 1.0}, {"source": "branches", "target": "gtk", "relation": "imports_from", "confidence": "EXTRACTED", "source_file": "src/linux_terminal/git/branches.rs", "source_location": "L3", "weight": 1.0}, {"source": "branches", "target": "super", "relation": "imports_from", "confidence": "EXTRACTED", "source_file": "src/linux_terminal/git/branches.rs", "source_location": "L8", "weight": 1.0}, {"source": "branches", "target": "branches_build_branches_view", "relation": "contains", "confidence": "EXTRACTED", "source_file": "src/linux_terminal/git/branches.rs", "source_location": "L13", "weight": 1.0}, {"source": "branches", "target": "branches_refresh_branches", "relation": "contains", "confidence": "EXTRACTED", "source_file": "src/linux_terminal/git/branches.rs", "source_location": "L113", "weight": 1.0}, {"source": "branches", "target": "branches_build_branch_row", "relation": "contains", "confidence": "EXTRACTED", "source_file": "src/linux_terminal/git/branches.rs", "source_location": "L144", "weight": 1.0}, {"source": "branches", "target": "branches_build_remote_branch_row", "relation": "contains", "confidence": "EXTRACTED", "source_file": "src/linux_terminal/git/branches.rs", "source_location": "L244", "weight": 1.0}, {"source": "branches", "target": "branches_clear_list", "relation": "contains", "confidence": "EXTRACTED", "source_file": "src/linux_terminal/git/branches.rs", "source_location": "L265", "weight": 1.0}, {"source": "branches", "target": "branches_branchwidgets", "relation": "contains", "confidence": "EXTRACTED", "source_file": "src/linux_terminal/git/branches.rs", "source_location": "L271", "weight": 1.0}, {"source": "branches_refresh_branches", "target": "branches_clear_list", "relation": "calls", "confidence": "EXTRACTED", "source_file": "src/linux_terminal/git/branches.rs", "source_location": "L119", "weight": 1.0}, {"source": "branches_refresh_branches", "target": "branches_build_branch_row", "relation": "calls", "confidence": "EXTRACTED", "source_file": "src/linux_terminal/git/branches.rs", "source_location": "L130", "weight": 1.0}, {"source": "branches_refresh_branches", "target": "branches_build_remote_branch_row", "relation": "calls", "confidence": "EXTRACTED", "source_file": "src/linux_terminal/git/branches.rs", "source_location": "L133", "weight": 1.0}]}